agentkernel_mongo/__init__.py
agentkernel_mongo/config.py
agentkernel_mongo/store.py
agentkernel_mongo-0.2.2.dist-info/METADATA
agentkernel_mongo-0.2.2.dist-info/WHEEL
agentkernel_mongo-0.2.2.dist-info/entry_points.txt
agentkernel_mongo-0.2.2.dist-info/top_level.txt
agentkernel_mongo-0.2.2.dist-info/RECORD
