Metadata-Version: 2.4
Name: agentkernel-mongo
Version: 0.2.2
Summary: MongoDB Session Store extension for Agent Kernel
Author-email: Dintih Kumudika <dinithwalpitagama@gmail.com>
Classifier: Programming Language :: Python :: 3
Classifier: License :: OSI Approved :: MIT License
Classifier: Operating System :: OS Independent
Requires-Python: >=3.12
Requires-Dist: agentkernel
Requires-Dist: pymongo>=4.0.0
